babelnet/__init__.py
babelnet/_impl.py
babelnet/_restful.py
babelnet/_utils.py
babelnet/about.py
babelnet/api.py
babelnet/conf.py
babelnet/language.py
babelnet/pos.py
babelnet/remote_server.py
babelnet/resources.py
babelnet/sense.py
babelnet/synset.py
babelnet/tag_utils.py
babelnet/versions.py
babelnet/zerorpc_patch.py
babelnet/apis/__init__.py
babelnet/apis/abstract_api.py
babelnet/apis/local_api.py
babelnet/apis/online_api.py
babelnet/apis/rpc_api.py
babelnet/data/__init__.py
babelnet/data/alphabet.py
babelnet/data/category.py
babelnet/data/compare.py
babelnet/data/domain.py
babelnet/data/entity_type.py
babelnet/data/example.py
babelnet/data/frame.py
babelnet/data/gloss.py
babelnet/data/image.py
babelnet/data/lemma.py
babelnet/data/license.py
babelnet/data/locale.py
babelnet/data/phonetics.py
babelnet/data/qcode.py
babelnet/data/relation.py
babelnet/data/source.py
babelnet/data/tag.py
babelnet/data/taggable.py
babelnet/data/tokens.py
babelnet/data/usage.py
babelnet/indices/__init__.py
babelnet/indices/index.py
babelnet/indices/local_index.py
babelnet/iterators/__init__.py
babelnet/iterators/abstract_iter.py
babelnet/iterators/iter_impl.py
babelnet/res/category_prefix.yml
babelnet/res/languages.yml
babelnet/res/pointer_v1.txt
babelnet/res/pointer_v2.txt
babelnet_rpc/__init__.py
babelnet_rpc/__main__.py
babelnet_rpc/constants.py
babelnet-1.2.0.dist-info/LICENSE
babelnet-1.2.0.dist-info/METADATA
babelnet-1.2.0.dist-info/WHEEL
babelnet-1.2.0.dist-info/entry_points.txt
babelnet-1.2.0.dist-info/top_level.txt
babelnet-1.2.0.dist-info/RECORD
