Metadata-Version: 2.1
Name: babelnet
Version: 1.2.0
Summary: Python API for BabelNet
Home-page: https://babelnet.org/
Author: Babelscape
Author-email: info@babelscape.com
Project-URL: Documentation, https://babelnet.org/pydoc/1.2/
Classifier: Programming Language :: Python :: 3.8
Classifier: Natural Language :: English
Classifier: Intended Audience :: Developers
Classifier: Intended Audience :: Education
Classifier: Intended Audience :: Science/Research
Classifier: Topic :: Text Processing :: Linguistic
Classifier: Topic :: Scientific/Engineering :: Artificial Intelligence
Classifier: License :: Other/Proprietary License
Classifier: Operating System :: OS Independent
Requires-Python: ==3.8.*
License-File: LICENSE
Requires-Dist: cloudpickle
Requires-Dist: zerorpc
Requires-Dist: pyzmq (!=23.0.*,>=22.3)
Requires-Dist: dataclasses
Requires-Dist: text-unidecode (>=1.2)
Requires-Dist: ordered-set (>=3.0.1)
Requires-Dist: requests (>=2.19.1)
Requires-Dist: pyyaml (>=4.2b4)
Requires-Dist: aenum (>=2.1.2)
Provides-Extra: rpc
Requires-Dist: docker ; extra == 'rpc'
